README.txt
setup.py
collective/__init__.py
collective.collection.alphabetic.egg-info/PKG-INFO
collective.collection.alphabetic.egg-info/SOURCES.txt
collective.collection.alphabetic.egg-info/dependency_links.txt
collective.collection.alphabetic.egg-info/entry_points.txt
collective.collection.alphabetic.egg-info/namespace_packages.txt
collective.collection.alphabetic.egg-info/not-zip-safe
collective.collection.alphabetic.egg-info/requires.txt
collective.collection.alphabetic.egg-info/top_level.txt
collective/collection/__init__.py
collective/collection/alphabetic/__init__.py
collective/collection/alphabetic/config.py
collective/collection/alphabetic/configure.zcml
collective/collection/alphabetic/interfaces.py
collective/collection/alphabetic/version.txt
collective/collection/alphabetic/browser/__init__.py
collective/collection/alphabetic/browser/category_alphabetic.py
collective/collection/alphabetic/browser/category_alphabetic_view.pt
collective/collection/alphabetic/browser/character_options.py
collective/collection/alphabetic/browser/configure.zcml
collective/collection/alphabetic/browser/topic_alphabetic.py
collective/collection/alphabetic/browser/topic_alphabetic_view.pt
collective/collection/alphabetic/browser/stylesheets/main.css
collective/collection/alphabetic/profiles/default/controlpanel.xml
collective/collection/alphabetic/profiles/default/cssregistry.xml
collective/collection/alphabetic/profiles/default/metadata.xml
collective/collection/alphabetic/profiles/default/propertiestool.xml
collective/collection/alphabetic/profiles/default/types/Topic.xml
collective/collection/alphabetic/tests/__init__.py
collective/collection/alphabetic/tests/base.py
collective/collection/alphabetic/tests/functional.txt
collective/collection/alphabetic/tests/test_doctest.py
collective/collection/alphabetic/tests/test_setup.py
collective/collection/alphabetic/tests/unittest.txt
collective/collection/alphabetic/utility/__init__.py
collective/collection/alphabetic/utility/character.py
collective/collection/alphabetic/utility/configure.zcml
docs/HISTORY.txt
docs/INSTALL.txt
docs/LICENSE.GPL
docs/LICENSE.txt