Metadata-Version: 1.0
Name: collective.collection.alphabetic
Version: 0.4.5
Summary: Add alphabetic view for collection.
Home-page: http://pypi.python.org/pypi/collective.collection.alphabetic/
Author: Taito Horiuchi
Author-email: taito.horiuchi@abita.fi
License: GPL
Platform: UNKNOWN
Classifier: Framework :: Plone
Classifier: Programming Language :: Python
Classifier: Topic :: Software Development :: Libraries :: Python Modules
